cqparts/__init__.py
cqparts/assembly.py
cqparts/component.py
cqparts/errors.py
cqparts/part.py
cqparts/search.py
cqparts/catalogue/__init__.py
cqparts/catalogue/catalogue.py
cqparts/catalogue/json.py
cqparts/codec/__init__.py
cqparts/codec/amf.py
cqparts/codec/gltf.py
cqparts/codec/step.py
cqparts/codec/stl.py
cqparts/codec/svg.py
cqparts/codec/threejs_json.py
cqparts/constraint/__init__.py
cqparts/constraint/base.py
cqparts/constraint/constraints.py
cqparts/constraint/mate.py
cqparts/constraint/solver.py
cqparts/display/__init__.py
cqparts/display/cqparts_server.py
cqparts/display/environment.py
cqparts/display/freecad.py
cqparts/display/material.py
cqparts/display/web.py
cqparts/display/web-template/README.md
cqparts/display/web-template/cqparts-display.txt
cqparts/display/web-template/index.html
cqparts/display/web-template/model/placeholder.txt
cqparts/display/web-template/static/js/GLTFLoader.js
cqparts/display/web-template/static/js/OrbitControls.js
cqparts/display/web-template/static/js/app.js
cqparts/display/web-template/static/js/orbit-controls-component.min.js
cqparts/display/web-template/static/js/three.min.js
cqparts/params/__init__.py
cqparts/params/parameter.py
cqparts/params/parametric_object.py
cqparts/params/types.py
cqparts/params/utils.py
cqparts/utils/__init__.py
cqparts/utils/geometry.py
cqparts/utils/misc.py
cqparts/utils/sphinx.py
cqparts/utils/test.py
cqparts/utils/wrappers.py
cqparts-0.2.1.dist-info/DESCRIPTION.rst
cqparts-0.2.1.dist-info/METADATA
cqparts-0.2.1.dist-info/RECORD
cqparts-0.2.1.dist-info/WHEEL
cqparts-0.2.1.dist-info/metadata.json
cqparts-0.2.1.dist-info/top_level.txt
