Metadata-Version: 2.0
Name: cqparts
Version: 0.2.1
Summary: Hierarchical and deeply parametric models using cadquery
Home-page: https://github.com/fragmuffin/cqparts
Author: Peter Boin
Author-email: peter.boin+cqparts@gmail.com
License: GPLv3
Keywords: cadquery,cad,3d,modeling
Platform: UNKNOWN
Classifier: Intended Audience :: Developers
Classifier: Intended Audience :: Manufacturing
Classifier: Intended Audience :: End Users/Desktop
Classifier: Intended Audience :: Science/Research
Classifier: License :: OSI Approved :: GNU General Public License v3 (GPLv3)
Classifier: Natural Language :: English
Classifier: Operating System :: MacOS
Classifier: Operating System :: POSIX
Classifier: Operating System :: Unix
Classifier: Programming Language :: Python
Classifier: Programming Language :: Python :: 2
Classifier: Programming Language :: Python :: 3
Classifier: Topic :: Scientific/Engineering
Classifier: Topic :: Multimedia :: Graphics :: 3D Modeling
Classifier: Topic :: Multimedia :: Graphics :: 3D Rendering
Classifier: Development Status :: 3 - Alpha
Requires-Dist: cadquery
Requires-Dist: six
Requires-Dist: numpy
Requires-Dist: Jinja2
Requires-Dist: tinydb
Requires-Dist: requests
